chinese_address_generator/__init__.py
chinese_address_generator/__main__.py
chinese_address_generator/cnaddrgen.py
chinese_address_generator/crawler.py
chinese_address_generator/generator.py
chinese_address_generator/src/new_level3.json
chinese_address_generator/src/new_level4.txt
chinese_address_generator-0.2.0.dist-info/LICENSE
chinese_address_generator-0.2.0.dist-info/METADATA
chinese_address_generator-0.2.0.dist-info/WHEEL
chinese_address_generator-0.2.0.dist-info/entry_points.txt
chinese_address_generator-0.2.0.dist-info/top_level.txt
chinese_address_generator-0.2.0.dist-info/RECORD
