Metadata-Version: 2.1
Name: chinese_address_generator
Version: 0.2.0
Summary: Random generation of Chinese place names
Home-page: https://github.com/Ginkgoty/chinese-address-generator/
Author: Ginkgoty
Author-email: int32@foxmail.com
License: MIT
Classifier: Intended Audience :: Developers
Classifier: License :: OSI Approved :: MIT License
Classifier: Programming Language :: Python :: 3
Classifier: Programming Language :: Python :: 3.7
Classifier: Programming Language :: Python :: 3.8
Classifier: Programming Language :: Python :: 3.9
Classifier: Programming Language :: Python :: 3.10
Classifier: Programming Language :: Python :: 3.11
Classifier: Programming Language :: Python :: 3.12
License-File: LICENSE
